gldpmclient/__init__.py
gldpmclient/client.py
gldpmclient/converters.py
gldpmclient/exceptions.py
gldpmclient/objects.py
gldpmclient/elements/__init__.py
gldpmclient/elements/esmp_active_power.py
gldpmclient/elements/esmp_date_time_interval.py
gldpmclient/elements/esmp_voltage.py
gldpmclient/elements/fault.py
gldpmclient/elements/mkt_generating_unit.py
gldpmclient/elements/mkt_psr_type.py
gldpmclient/elements/point.py
gldpmclient/elements/series_period.py
gldpmclient/elements/time_series.py
gldpmclient/enums/__init__.py
gldpmclient/enums/asset_type.py
gldpmclient/enums/business_type.py
gldpmclient/enums/coding_scheme.py
gldpmclient/enums/curve_type.py
gldpmclient/enums/indicator_type.py
gldpmclient/enums/message_type.py
gldpmclient/enums/object_aggregation_type.py
gldpmclient/enums/process_type.py
gldpmclient/enums/role_type.py
gldpmclient/enums/unit_of_measure_type.py
gldpmclient/enums/unit_symbol.py
gldpmclient/messages/__init__.py
gldpmclient/messages/acknowledgement_market_document_response.py
gldpmclient/messages/gl_market_document.py
gldpmclient/messages/gl_market_document_body.py
gldpmclient/messages/gl_market_document_response.py
gldpmclient/messages/is_alive_request.py
gldpmclient/messages/is_alive_response.py
gldpmclient/messages/mmc_hub_response.py
gldpmclient/metadata/__init__.py
gldpmclient/metadata/id_strings.py
gldpmclient/metadata/message_addressing.py
gldpmclient/metadata/version.py
gldpmclient-1.3.0.dist-info/LICENSE
gldpmclient-1.3.0.dist-info/METADATA
gldpmclient-1.3.0.dist-info/WHEEL
gldpmclient-1.3.0.dist-info/top_level.txt
gldpmclient-1.3.0.dist-info/RECORD
