Metadata-Version: 2.1
Name: gldpmclient
Version: 1.3.0
Summary: Generation Load Data Providison Methodology client for Python
License: Apache License
Requires-Python: >=3.10
License-File: LICENSE
Requires-Dist: requests
Requires-Dist: xsdata
Requires-Dist: tzdata ; os_name == "nt"
Provides-Extra: dev
Requires-Dist: pytest ; extra == 'dev'
Requires-Dist: pytest-cov ; extra == 'dev'
